taeyun/app.py
Lee_Tae_Yun_OSS-0.0.1.dist-info/METADATA
Lee_Tae_Yun_OSS-0.0.1.dist-info/WHEEL
Lee_Tae_Yun_OSS-0.0.1.dist-info/top_level.txt
Lee_Tae_Yun_OSS-0.0.1.dist-info/RECORD
