Metadata-Version: 2.1
Name: Lee-Tae-Yun-OSS
Version: 0.0.1
Summary: oss-dev my calculator 0001
Home-page: https://github.com/Lee-Tae-Yun/Donga_oss
Download-URL: https://github.com/Lee-Tae-Yun/Donga_oss/archive/refs/tags/v0.0.1.zip
Author: leetaeyun
Author-email: cmskzkdl3698@naver.com
Classifier: Programming Language :: Python :: 3
Classifier: Operating System :: OS Independent
Requires-Dist: pytest
